roshi/__init__.py
roshi/roshi.py
roshi-1.2.7.dist-info/METADATA
roshi-1.2.7.dist-info/RECORD
roshi-1.2.7.dist-info/WHEEL
roshi-1.2.7.dist-info/top_level.txt
