Metadata-Version: 2.1
Name: roshi
Version: 1.2.7
Summary: UNKNOWN
Home-page: https://github.com/Bukkaraya/Roshi
Author: Abinav Bukkaraya
Author-email: abinavbukkaraya@gmail.com
License: MIT
Platform: UNKNOWN
